nasunitest/__init__.py
nasunitest/py.typed
nasunitest-0.1.1.dist-info/WHEEL
nasunitest-0.1.1.dist-info/METADATA
nasunitest-0.1.1.dist-info/RECORD
