Metadata-Version: 2.1
Name: nasunitest
Version: 0.1.1
Summary: Test cookiecutter project
Home-page: https://dterrynasuni.github.io/nasunitest
License: MIT
Author: Dylan Terry
Author-email: dterry@nasuni.com
Requires-Python: >=3.7.1,<4.0
Classifier: Development Status :: 4 - Beta
Classifier: Intended Audience :: Developers
Classifier: License :: OSI Approved :: MIT License
Classifier: Operating System :: OS Independent
Classifier: Programming Language :: Python
Classifier: Programming Language :: Python :: 3
Classifier: Programming Language :: Python :: 3.10
Classifier: Programming Language :: Python :: 3.7
Classifier: Programming Language :: Python :: 3.8
Classifier: Programming Language :: Python :: 3.9
Classifier: Topic :: Software Development :: Libraries :: Python Modules
Classifier: Typing :: Typed
Project-URL: Documentation, https://dterrynasuni.github.io/nasunitest
Project-URL: Repository, https://github.com/dterrynasuni/nasunitest
